drf_lookup/__init__.py
drf_lookup/lookup.py
drf_lookup/serializers.py
drf_lookup/settings.py
drf_lookup/utils.py
drf_lookup/views.py
drf_lookup/handlers/__init__.py
drf_lookup/handlers/base.py
drf_lookup/handlers/boolean.py
drf_lookup/handlers/choices.py
drf_lookup/handlers/queryset.py
drf_lookup-1.0.1.dist-info/METADATA
drf_lookup-1.0.1.dist-info/WHEEL
drf_lookup-1.0.1.dist-info/licenses/LICENSE
drf_lookup-1.0.1.dist-info/RECORD
