Metadata-Version: 2.4
Name: drf-lookup
Version: 1.0.1
Summary: Helper for retrieve select options of drf fields and django-filter filters.
Project-URL: Homepage, https://github.com/kindlycat/drf-lookup
Project-URL: Documentation, https://drf-lookup.readthedocs.io
Project-URL: Repository, https://github.com/kindlycat/drf-lookup.git
Project-URL: Issues, https://github.com/kindlycat/drf-lookup/issues
Author-email: Grigory Mishchenko <grishkokot@gmail.com>
License-Expression: MIT
License-File: LICENSE
Keywords: django-filter,drf
Classifier: Development Status :: 5 - Production/Stable
Classifier: Framework :: Django
Classifier: License :: OSI Approved :: MIT License
Classifier: Programming Language :: Python :: 3.10
Classifier: Programming Language :: Python :: 3.11
Classifier: Programming Language :: Python :: 3.12
Requires-Python: >=3.10
Requires-Dist: django-filter>=23.0
Requires-Dist: djangorestframework>=3.14.0
